perfprof/__init__.py
perfprof/perfprof.py
perfprof-0.2.dist-info/LICENSE
perfprof-0.2.dist-info/METADATA
perfprof-0.2.dist-info/WHEEL
perfprof-0.2.dist-info/top_level.txt
perfprof-0.2.dist-info/RECORD
