Metadata-Version: 2.1
Name: perfprof
Version: 0.2
Summary: A Python package for performance profiles as defined by Dolan and More.
Home-page: https://github.com/dmsteck/perfprof.py
Author: Daniel Steck
Author-email: daniel.m.steck@gmail.com
License: MIT license
Project-URL: Bug Tracker, https://github.com/dmsteck/perfprof.py/issues
Keywords: profile,benchmark,performance,algorithms,optimization,Dolan,More
Platform: UNKNOWN
Classifier: Programming Language :: Python :: 3
Classifier: License :: OSI Approved :: MIT License
Classifier: Operating System :: OS Independent
Requires-Python: >=3.6
